docling_graph/__init__.py
docling_graph/config.py
docling_graph/exceptions.py
docling_graph/pipeline.py
docling_graph/protocols.py
docling_graph/cli/__init__.py
docling_graph/cli/config_builder.py
docling_graph/cli/config_utils.py
docling_graph/cli/constants.py
docling_graph/cli/dependencies.py
docling_graph/cli/main.py
docling_graph/cli/validators.py
docling_graph/cli/commands/__init__.py
docling_graph/cli/commands/convert.py
docling_graph/cli/commands/init.py
docling_graph/cli/commands/inspect.py
docling_graph/core/__init__.py
docling_graph/core/converters/__init__.py
docling_graph/core/converters/config.py
docling_graph/core/converters/graph_converter.py
docling_graph/core/converters/models.py
docling_graph/core/converters/node_id_registry.py
docling_graph/core/exporters/__init__.py
docling_graph/core/exporters/base.py
docling_graph/core/exporters/csv_exporter.py
docling_graph/core/exporters/cypher_exporter.py
docling_graph/core/exporters/docling_exporter.py
docling_graph/core/exporters/json_exporter.py
docling_graph/core/extractors/__init__.py
docling_graph/core/extractors/chunk_batcher.py
docling_graph/core/extractors/document_chunker.py
docling_graph/core/extractors/document_processor.py
docling_graph/core/extractors/extractor_base.py
docling_graph/core/extractors/factory.py
docling_graph/core/extractors/backends/__init__.py
docling_graph/core/extractors/backends/llm_backend.py
docling_graph/core/extractors/backends/vlm_backend.py
docling_graph/core/extractors/strategies/__init__.py
docling_graph/core/extractors/strategies/many_to_one.py
docling_graph/core/extractors/strategies/one_to_one.py
docling_graph/core/input/__init__.py
docling_graph/core/input/handlers.py
docling_graph/core/input/types.py
docling_graph/core/input/validators.py
docling_graph/core/utils/__init__.py
docling_graph/core/utils/dict_merger.py
docling_graph/core/utils/graph_cleaner.py
docling_graph/core/utils/io_optimizer.py
docling_graph/core/utils/output_manager.py
docling_graph-1.2.3.dist-info/licenses/LICENSE
docling_graph-1.2.3.dist-info/METADATA
docling_graph-1.2.3.dist-info/WHEEL
docling_graph-1.2.3.dist-info/entry_points.txt
docling_graph-1.2.3.dist-info/top_level.txt
docling_graph-1.2.3.dist-info/RECORD
