Metadata-Version: 2.4
Name: docling_graph
Version: 1.2.3
Summary: A tool to convert documents into knowledge graphs using Docling.
Author-email: Ayoub El Bouchtili <ayoub.elbouchtili@fr.ibm.com>, Michele Dolfi <dol@zurich.ibm.com>, Maxime Gillot <Maxime.Gillot@ibm.com>, Sophie Lang <sophie.lang@de.ibm.com>, Guilhaume Leroy Meline <guilhaume@fr.ibm.com>, Peter Staar <taa@zurich.ibm.com>
License: MIT License
Project-URL: homepage, https://github.com/ayoub-ibm/docling-graph
Project-URL: repository, https://github.com/ayoub-ibm/docling-graph
Project-URL: issues, https://github.com/ayoub-ibm/docling-graph/issues
Project-URL: changelog, https://github.com/ayoub-ibm/docling-graph/blob/main/CHANGELOG.md
Keywords: docling,knowledge-graph,nlp,pdf,graph
Classifier: Operating System :: MacOS :: MacOS X
Classifier: Operating System :: POSIX :: Linux
Classifier: Operating System :: Microsoft :: Windows
Classifier: Intended Audience :: Developers
Classifier: Programming Language :: Python :: 3
Classifier: Programming Language :: Python :: 3.10
Classifier: Programming Language :: Python :: 3.11
Classifier: Programming Language :: Python :: 3.12
Classifier: Programming Language :: Python :: 3.13
Requires-Python: <4.0,>=3.10
License-File: LICENSE
Requires-Dist: docling[vlm]<3.0.0,>=2.70.0
Requires-Dist: docling-core[chunking,chunking-openai]<3.0.0,>=2.50.0
Requires-Dist: pydantic<3.0.0,>=2.0.0
Requires-Dist: networkx<4.0.0,>=3.0.0
Requires-Dist: rich<15,>=13
Requires-Dist: typer[all]<1.0.0,>=0.12
Requires-Dist: python-dotenv<2.0,>=1.0
Requires-Dist: pyyaml<7.0,>=6.0
Requires-Dist: aiofiles<26.0.0,>=24.0.0
Provides-Extra: ollama
Requires-Dist: ollama; extra == "ollama"
Provides-Extra: vllm
Requires-Dist: openai; extra == "vllm"
Provides-Extra: gemini
Requires-Dist: google-genai; extra == "gemini"
Provides-Extra: mistral
Requires-Dist: mistralai; extra == "mistral"
Provides-Extra: openai
Requires-Dist: openai; extra == "openai"
Provides-Extra: watsonx
Requires-Dist: ibm-watsonx-ai; extra == "watsonx"
Provides-Extra: local
Requires-Dist: docling-graph[ollama]; extra == "local"
Requires-Dist: docling-graph[vllm]; extra == "local"
Provides-Extra: remote
Requires-Dist: docling-graph[openai]; extra == "remote"
Requires-Dist: docling-graph[mistral]; extra == "remote"
Requires-Dist: docling-graph[gemini]; extra == "remote"
Requires-Dist: docling-graph[watsonx]; extra == "remote"
Provides-Extra: all
Requires-Dist: docling-graph[local]; extra == "all"
Requires-Dist: docling-graph[remote]; extra == "all"
Dynamic: license-file
